LICENSE.txt
MANIFEST.in
README.md
setup.py
jk_testing/Assert.py
jk_testing/AssertX.py
jk_testing/AssertionException.py
jk_testing/EnumEnabledState.py
jk_testing/EnumProcessingState.py
jk_testing/NodeMatrix.py
jk_testing/SingleLookAtQueue.py
jk_testing/TestCaseCollection.py
jk_testing/TestCaseInstance.py
jk_testing/TestCollectionVisualizer.py
jk_testing/TestContext.py
jk_testing/TestDriver.py
jk_testing/TestReporterHTML.py
jk_testing/TestResult.py
jk_testing/TestResultCollection.py
jk_testing/_TestToRun.py
jk_testing/__OLD_TestCaseCollection.py
jk_testing/__init__.py
jk_testing/__test-NodeMatrix.py
jk_testing.egg-info/PKG-INFO
jk_testing.egg-info/SOURCES.txt
jk_testing.egg-info/dependency_links.txt
jk_testing.egg-info/not-zip-safe
jk_testing.egg-info/requires.txt
jk_testing.egg-info/top_level.txt
jk_testing/annotations/Description.py
jk_testing/annotations/ProvidesVariable.py
jk_testing/annotations/RaisesException.py
jk_testing/annotations/Requires.py
jk_testing/annotations/RequiresVariable.py
jk_testing/annotations/RunAfter.py
jk_testing/annotations/RunBefore.py
jk_testing/annotations/TestCase.py
jk_testing/annotations/__init__.py
jk_testing/data/html_default/files/jquery-3.3.1.min.js
jk_testing/data/html_default/files/jquery-ui-1.12.1.min.css
jk_testing/data/html_default/files/jquery-ui-1.12.1.min.js
jk_testing/data/html_default/files/styles.css
jk_testing/data/html_default/files/images/ui-icons_444444_256x240.png
jk_testing/data/html_default/files/images/ui-icons_555555_256x240.png
jk_testing/data/html_default/files/images/ui-icons_777620_256x240.png
jk_testing/data/html_default/files/images/ui-icons_777777_256x240.png
jk_testing/data/html_default/files/images/ui-icons_cc0000_256x240.png
jk_testing/data/html_default/files/images/ui-icons_ffffff_256x240.png
jk_testing/data/html_default/templates/index.html
jk_testing/data/html_default/templates/testcase.html
jk_testing/impl/ExceptionMatcher.py
jk_testing/impl/__init__.py
jk_testing/utils/OutputComparison.py
jk_testing/utils/SimpleTextLineOutputBuffer.py
jk_testing/utils/StringList.py
jk_testing/utils/StringListDiff.py
jk_testing/utils/StringUtils.py
jk_testing/utils/__init__.py