Metadata-Version: 2.1
Name: jk-testing
Version: 0.2022.8.6
Summary: This python module provides a simple to use infrastructure for running unit tests.
Home-page: UNKNOWN
Author: Jürgen Knauth
Author-email: pubsrc@binary-overflow.de
License: Apache2
Keywords: testing,unittests,tests
Platform: UNKNOWN
Classifier: Development Status :: 5 - Production/Stable
Classifier: License :: OSI Approved :: Apache Software License
Classifier: Programming Language :: Python :: 3
Classifier: Topic :: Software Development :: Testing
